distribute2mpi.py
distribute2mpi-0.3.1.dist-info/DESCRIPTION.rst
distribute2mpi-0.3.1.dist-info/METADATA
distribute2mpi-0.3.1.dist-info/RECORD
distribute2mpi-0.3.1.dist-info/WHEEL
distribute2mpi-0.3.1.dist-info/metadata.json
distribute2mpi-0.3.1.dist-info/top_level.txt
