Metadata-Version: 2.0
Name: distribute2mpi
Version: 0.3.1
Summary: Multiprocessing for HPC system using MPI
Home-page: https://github.com/poquirion/distribute2mpi/
Author: P.-O. Quirion
Author-email: pioliqui@gmail.com
License: MIT
Platform: UNKNOWN
Classifier: Development Status :: 4 - Beta
Classifier: Intended Audience :: Developers
Classifier: License :: OSI Approved :: MIT License
Classifier: Programming Language :: Python :: 2
Classifier: Programming Language :: Python :: 2.7
Classifier: Programming Language :: Python :: 3
Classifier: Programming Language :: Python :: 3.3
Classifier: Programming Language :: Python :: 3.4
Classifier: Programming Language :: Python :: 3.5
Requires-Dist: dill
Requires-Dist: mpi4py
Requires-Dist: psutil
